compy_bridge_lib_glfw/d_types.py
compy_bridge_lib_glfw/compy_data/bridge_jsons/always_pass_by_value.json
compy_bridge_lib_glfw/compy_data/bridge_jsons/attr_map.json
compy_bridge_lib_glfw/compy_data/bridge_jsons/call_map.json
compy_bridge_lib_glfw/compy_data/bridge_jsons/cmake_lists.json
compy_bridge_lib_glfw/compy_data/bridge_jsons/import_map.json
compy_bridge_lib_glfw/compy_data/bridge_jsons/name_map.json
compy_bridge_lib_glfw/compy_data/cpp/hello_world.cpp
compy_bridge_lib_glfw/compy_data/cpp/hello_world.h
compy_bridge_lib_glfw-0.0.2.dist-info/METADATA
compy_bridge_lib_glfw-0.0.2.dist-info/WHEEL
compy_bridge_lib_glfw-0.0.2.dist-info/licenses/LICENSE
compy_bridge_lib_glfw-0.0.2.dist-info/RECORD
