Metadata-Version: 2.4
Name: compy-bridge-lib-glfw
Version: 0.0.2
Summary: a Compy bridge-library for glfw
Project-URL: Homepage, https://github.com/curtispuetz/compy-bridge-lib-glfw
Author-email: Curtis Puetz <compy.main@gmail.com>
License: MIT
License-File: LICENSE
Requires-Python: >=3.13
Requires-Dist: glfw==2.9.0
